PySkeletor-0.1.dist-info/DESCRIPTION.rst
PySkeletor-0.1.dist-info/METADATA
PySkeletor-0.1.dist-info/RECORD
PySkeletor-0.1.dist-info/WHEEL
PySkeletor-0.1.dist-info/entry_points.txt
PySkeletor-0.1.dist-info/metadata.json
PySkeletor-0.1.dist-info/top_level.txt
skeletor/__init__.py
skeletor/__main__.py
skeletor/cli/__init__.py
skeletor/cli/main.py
