Metadata-Version: 2.0
Name: PySkeletor
Version: 0.1
Summary: A fairly complete Python boilerplate project
Home-page: https://github.com/rdhushyanth/Skeletor
Author: Dhushyanth Ramasamy
Author-email: pypi@dhushyanth.com
License: UNKNOWN
Platform: UNKNOWN
Classifier: Development Status :: 3 - Alpha
Classifier: Intended Audience :: Developers
Classifier: Topic :: Software Development :: Build Tools
Classifier: License :: OSI Approved :: MIT License
Classifier: Programming Language :: Python :: 3
Classifier: Programming Language :: Python :: 3.4
Classifier: Programming Language :: Python :: 3.5
Classifier: Programming Language :: Python :: 3.6
Requires-Dist: click
